codeenigma/__init__.py
codeenigma/bundler/__init__.py
codeenigma/bundler/base.py
codeenigma/bundler/poetry.py
codeenigma/bundler/standard.py
codeenigma/cli.py
codeenigma/executor.py.template
codeenigma/extensions/__init__.py
codeenigma/extensions/base.py
codeenigma/extensions/expiry.py
codeenigma/extensions/expiry_code.py.template
codeenigma/orchestrator.py
codeenigma/private.py
codeenigma/runtime/__init__.py
codeenigma/runtime/base.py
codeenigma/runtime/cython/__init__.py
codeenigma/runtime/cython/builder.py
codeenigma/runtime/cython/init.py.template
codeenigma/runtime/cython/pyproject.toml.template
codeenigma/runtime/cython/setup.py.template
codeenigma/strategies/__init__.py
codeenigma/strategies/base.py
codeenigma/strategies/encryption.py
codeenigma/strategies/encryption_runtime.py.template
codeenigma-1.2.0.dist-info/LICENSE
codeenigma-1.2.0.dist-info/METADATA
codeenigma-1.2.0.dist-info/WHEEL
codeenigma-1.2.0.dist-info/entry_points.txt
codeenigma-1.2.0.dist-info/RECORD
