Metadata-Version: 2.3
Name: codeenigma
Version: 1.2.0
Summary: A lightweight, open-source tool for Python code obfuscation. CodeEnigma helps protect your logic from reverse engineering and unauthorized access, making it a practical alternative to PyArmor for securely distributing your Python applications
License: MIT
Keywords: obfuscation,code protection,python security,pyarmor alternative,secure distribution
Author: Krishnan S G
Author-email: krishsg525@gmail.com
Requires-Python: >=3.10,<3.14
Classifier: Intended Audience :: Developers
Classifier: License :: OSI Approved :: MIT License
Classifier: Operating System :: OS Independent
Classifier: Programming Language :: Python
Classifier: Programming Language :: Python :: 3
Classifier: Programming Language :: Python :: 3.10
Classifier: Programming Language :: Python :: 3.11
Classifier: Programming Language :: Python :: 3.12
Classifier: Programming Language :: Python :: 3.13
Classifier: Topic :: Security
Classifier: Topic :: Software Development :: Libraries
Classifier: Topic :: Utilities
Requires-Dist: cryptography (>=40.0.4)
Requires-Dist: cython (>=3.0.0)
Requires-Dist: poetry (>=2.0.0)
Requires-Dist: rich (>=13.0.0)
Requires-Dist: setuptools (>=70.0.0)
Requires-Dist: toml (>=0.9.2)
Requires-Dist: typer[all] (>=0.14.0)
Project-URL: Homepage, https://github.com/KrishnanSG/codeenigma
Project-URL: Source, https://github.com/KrishnanSG/codeenigma
Project-URL: Tracker, https://github.com/KrishnanSG/codeenigma/issues
